{
    "namespace": "urn:ietf:params:xml:ns:netconf:base:1.0",
    "inputs": {
        "persist-id": {
            "type": {
                "ptype": "str"
            },
            "isList": false,
            "description": "This parameter is given in order to cancel a persistent\nconfirmed commit.  The value must be equal to the value\ngiven in the 'persist' parameter to the <commit> operation.\nIf it does not match, the operation fails with an\n'invalid-value' error.",
            "mandatory": false
        }
    },
    "cases": {}
}